go_auth/__init__.py
go_auth/bouncer.py
go_auth/validator.py
go_auth/tests/__init__.py
go_auth/tests/test_bouncer.py
go_auth/tests/test_validator.py
go_auth-0.1.3.dist-info/DESCRIPTION.rst
go_auth-0.1.3.dist-info/METADATA
go_auth-0.1.3.dist-info/metadata.json
go_auth-0.1.3.dist-info/RECORD
go_auth-0.1.3.dist-info/top_level.txt
go_auth-0.1.3.dist-info/WHEEL
