Metadata-Version: 2.0
Name: go-auth
Version: 0.1.3
Summary: Authentication services and utilities for Vumi Go APIs.
Home-page: https://github.com/praekelt/go-auth
Author: Praekelt Foundation
Author-email: dev@praekeltfoundation.org
License: BSD
Platform: UNKNOWN
Classifier: Development Status :: 4 - Beta
Classifier: Intended Audience :: Developers
Classifier: License :: OSI Approved :: BSD License
Classifier: Operating System :: POSIX
Classifier: Programming Language :: Python
Classifier: Topic :: Software Development :: Libraries :: Python Modules
Classifier: Topic :: Internet :: WWW/HTTP
Requires-Dist: cyclone
Requires-Dist: oauthlib
Requires-Dist: go-api
Requires-Dist: PyYAML
